harp/serial/__init__.py
harp/serial/device.py
harp/serial/harp_serial.py
harp_serial-0.4.0.dist-info/WHEEL
harp_serial-0.4.0.dist-info/METADATA
harp_serial-0.4.0.dist-info/RECORD
